LICENSE
MANIFEST.in
README.md
package.json
setup.py
dash_nlp_components/ComponentBase.py
dash_nlp_components/__init__.py
dash_nlp_components/_imports_.py
dash_nlp_components/dash_nlp_components.min.js
dash_nlp_components/dash_nlp_components.min.js.map
dash_nlp_components/metadata.json
dash_nlp_components/package-info.json
dash_nlp_components.egg-info/PKG-INFO
dash_nlp_components.egg-info/SOURCES.txt
dash_nlp_components.egg-info/dependency_links.txt
dash_nlp_components.egg-info/top_level.txt