Metadata-Version: 2.1
Name: dash-nlp-components
Version: 0.0.1
Summary: TODO
Home-page: UNKNOWN
Author: Yasas Wijesu <yasas.mason@gmail.com>
License: MIT
Platform: UNKNOWN
Classifier: Framework :: Dash
License-File: LICENSE
